{
  "scoring_weights": {
    "role_balance": {
      "weight": 20,
      "description": "Score based on role distribution in the comp",
      "breakdown": {
        "has_controller": 7,
        "has_initiator": 5,
        "has_sentinel": 5,
        "duelist_count_optimal": 3
      }
    },
    "map_fit": {
      "weight": 15,
      "description": "Agents match the map via good_maps OR S/A meta tier",
      "breakdown": {
        "per_agent_on_good_map": 3,
        "max_possible": 15
      }
    },
    "synergy": {
      "weight": 20,
      "description": "Complementary combos (entry+flash, smokes+entry, recon+entry, anchor+flank, post-plant+zone) plus shared-tag cohesion",
      "breakdown": {
        "entry_plus_flash": 4,
        "smokes_plus_entry": 3,
        "recon_plus_entry": 3,
        "anchor_plus_flank": 3,
        "postplant_plus_zone": 3,
        "shared_tag_cap": 4
      }
    },
    "utility_coverage": {
      "weight": 15,
      "description": "Coverage of key utility types",
      "breakdown": {
        "has_smokes": 5,
        "has_recon": 4,
        "has_flash": 3,
        "has_post_plant": 3
      }
    },
    "attack_strength": {
      "weight": 10,
      "description": "Offensive capability of the comp",
      "breakdown": {
        "entry_tag": 5,
        "aggressive_tag": 3,
        "flash_for_entry": 2
      }
    },
    "defense_strength": {
      "weight": 10,
      "description": "Defensive capability (anchor/site-control, defensive/zone-control, flank-control)",
      "breakdown": {
        "anchor_tag": 4,
        "defensive_tag": 3,
        "flank_control_tag": 3
      }
    },
    "meta_alignment": {
      "weight": 10,
      "description": "Bonus for agents with S/A/B meta tier on the selected map (from VCT data)",
      "breakdown": {
        "s_tier_per_agent": 2,
        "a_tier_per_agent": 1.5,
        "b_tier_per_agent": 0.75
      }
    }
  },
  "penalties": {
    "no_controller": -15,
    "no_initiator": -10,
    "no_sentinel": -10,
    "too_many_duelists": -8,
    "no_smokes": -12,
    "no_recon": -8,
    "no_flash": -5,
    "no_entry": -6,
    "low_map_fit": -5
  },
  "warnings": {
    "no_controller": "No Controller selected — your team lacks smokes for site executes.",
    "no_initiator": "No Initiator selected — your team lacks opening utility and information.",
    "no_sentinel": "No Sentinel selected — your team has no site anchor or flank coverage.",
    "too_many_duelists": "Too many Duelists (3+) — your team lacks utility and support.",
    "no_entry_duelist": "No entry-focused Duelist — who is opening site?",
    "no_smokes": "No Controller smokes in your comp — you cannot safely execute sites.",
    "no_recon": "No recon utility — your team is playing blind.",
    "no_post_plant": "No post-plant utility — you may struggle to secure rounds.",
    "no_flank_control": "No flank control — your team is vulnerable to rotations.",
    "low_map_fit": "Several agents are not ideal for this map."
  },
  "preset_templates": {
    "Standard": {
      "description": "Balanced comp with clear roles",
      "role_counts": {"Duelist": 1, "Controller": 1, "Initiator": 2, "Sentinel": 1}
    },
    "Double Controller": {
      "description": "High utility and smoke coverage",
      "role_counts": {"Duelist": 1, "Controller": 2, "Initiator": 1, "Sentinel": 1}
    },
    "Double Duelist": {
      "description": "Aggressive, entry-heavy composition",
      "role_counts": {"Duelist": 2, "Controller": 1, "Initiator": 1, "Sentinel": 1}
    },
    "Info Heavy": {
      "description": "Maximum information and utility",
      "role_counts": {"Duelist": 1, "Controller": 1, "Initiator": 2, "Sentinel": 1}
    }
  }
}
